b3_scrapers/__init__.py
b3_scrapers/codigos_cvm.py
b3_scrapers/codigos_negociacao.py
b3_scrapers/eventos_acoes.py
b3_scrapers/eventos_fii.py
b3_scrapers/fii_listados.py
b3_scrapers/negociacao.py
b3_scrapers/proventos_fii.py
b3_scrapers-0.7.dist-info/METADATA
b3_scrapers-0.7.dist-info/WHEEL
b3_scrapers-0.7.dist-info/top_level.txt
b3_scrapers-0.7.dist-info/RECORD
